qfib/__init__.py
qfib/module1.py
tests/__init__.py
tests/test_module1.py
qfib-0.1.1.dist-info/LICENSE.py
qfib-0.1.1.dist-info/METADATA
qfib-0.1.1.dist-info/WHEEL
qfib-0.1.1.dist-info/top_level.txt
qfib-0.1.1.dist-info/RECORD
