Metadata-Version: 2.1
Name: qfib
Version: 0.1.1
Summary: Fibonacci number generator
Author: Freek van Keulen
Author-email: freek@quidome.nl
Classifier: Programming Language :: Python :: 3
Classifier: License :: OSI Approved :: MIT License
Classifier: Operating System :: OS Independent
Requires-Python: >=3.6
License-File: LICENSE.py
